Metadata-Version: 1.0
Name: mecha-distributions
Version: 0.3
Summary: Gaussian distributions
Home-page: UNKNOWN
Author: UNKNOWN
Author-email: UNKNOWN
License: UNKNOWN
Platform: UNKNOWN
